easy_regex/__init__.py
easy_regex/dates.py
easy_regex/email.py
easy_regex-0.0.3.dist-info/LICENSE
easy_regex-0.0.3.dist-info/METADATA
easy_regex-0.0.3.dist-info/WHEEL
easy_regex-0.0.3.dist-info/top_level.txt
easy_regex-0.0.3.dist-info/RECORD
